vimeodownload/__init__.py
vimeodownload/downloader.py
vimeodownload.py-0.0.2.dist-info/LICENSE.md
vimeodownload.py-0.0.2.dist-info/METADATA
vimeodownload.py-0.0.2.dist-info/WHEEL
vimeodownload.py-0.0.2.dist-info/top_level.txt
vimeodownload.py-0.0.2.dist-info/RECORD
