Metadata-Version: 2.1
Name: vimeodownload.py
Version: 0.0.2
Summary: Download videos from Vimeo
Home-page: https://github.com/jamiegyoung/vimeodownload.py
Author: jamiegyoung
License: UNKNOWN
Keywords: python,video,vimeo,download
Platform: UNKNOWN
Classifier: Development Status :: 3 - Alpha
Classifier: Intended Audience :: Developers
Classifier: Programming Language :: Python :: 3
Classifier: License :: OSI Approved :: MIT License
Classifier: Operating System :: OS Independent
Classifier: Topic :: Internet
Classifier: Topic :: Multimedia :: Video
Classifier: Topic :: Software Development :: Libraries :: Python Modules
Requires-Dist: requests (<3,>=2)
